trytond/modules/health_who_essential_medicines/COPYING
trytond/modules/health_who_essential_medicines/README.rst
trytond/modules/health_who_essential_medicines/__init__.py
trytond/modules/health_who_essential_medicines/data/WHO_list_of_essential_medicines.xml
trytond/modules/health_who_essential_medicines/data/WHO_products.xml
trytond/modules/health_who_essential_medicines/data/medicament_categories.xml
trytond/modules/health_who_essential_medicines/health_who_essential_medicines.py
trytond/modules/health_who_essential_medicines/locale/ar.po
trytond/modules/health_who_essential_medicines/locale/de.po
trytond/modules/health_who_essential_medicines/locale/el.po
trytond/modules/health_who_essential_medicines/locale/eo.po
trytond/modules/health_who_essential_medicines/locale/es.po
trytond/modules/health_who_essential_medicines/locale/fr.po
trytond/modules/health_who_essential_medicines/locale/health_who_essential_medicines.pot
trytond/modules/health_who_essential_medicines/locale/it_IT.po
trytond/modules/health_who_essential_medicines/locale/ja_JP.po
trytond/modules/health_who_essential_medicines/locale/ka.po
trytond/modules/health_who_essential_medicines/locale/lo.po
trytond/modules/health_who_essential_medicines/locale/pt_BR.po
trytond/modules/health_who_essential_medicines/locale/sv.po
trytond/modules/health_who_essential_medicines/locale/tr.po
trytond/modules/health_who_essential_medicines/locale/uk.po
trytond/modules/health_who_essential_medicines/locale/zh_CN.po
trytond/modules/health_who_essential_medicines/pyproject.toml
trytond/modules/health_who_essential_medicines/tests/__init__.py
trytond/modules/health_who_essential_medicines/tests/test_health_who_essential_medicines.py
trytond/modules/health_who_essential_medicines/tryton.cfg
gnuhealth_who_essential_medicines-5.0.2.dist-info/METADATA
gnuhealth_who_essential_medicines-5.0.2.dist-info/WHEEL
gnuhealth_who_essential_medicines-5.0.2.dist-info/licenses/COPYING
gnuhealth_who_essential_medicines-5.0.2.dist-info/RECORD
